header_printer/__init__.py
header_printer/printer.py
header_printer-0.0.7.dist-info/LICENSE
header_printer-0.0.7.dist-info/METADATA
header_printer-0.0.7.dist-info/WHEEL
header_printer-0.0.7.dist-info/top_level.txt
header_printer-0.0.7.dist-info/RECORD
