Metadata-Version: 2.1
Name: header-printer
Version: 0.0.7
Summary: Python package for printing a nicely formatted header.
Home-page: https://github.com/Michael-Wisniewski/header-printer
Author: Michał Wiśniewski
License: UNKNOWN
Project-URL: Documentation, https://github.com/Michael-Wisniewski/header-printer
Platform: UNKNOWN
Classifier: Programming Language :: Python :: 3.6
Classifier: Programming Language :: Python :: 3.7
Classifier: Programming Language :: Python :: 3.8
Classifier: Programming Language :: Python :: 3.9
Classifier: Programming Language :: Python :: 3.10
Classifier: License :: OSI Approved :: MIT License
Requires-Python: >=3.6
Provides-Extra: dev
Requires-Dist: black (==21.12b0) ; extra == 'dev'
Requires-Dist: check-manifest (==0.47) ; extra == 'dev'
Requires-Dist: coverage-badge (==1.1.0) ; extra == 'dev'
Requires-Dist: flake8 (==4.0.1) ; extra == 'dev'
Requires-Dist: isort (==5.10.1) ; extra == 'dev'
Requires-Dist: tox (==3.24.5) ; extra == 'dev'
Requires-Dist: twine (==3.7.1) ; extra == 'dev'
